trainplot/__init__.py
trainplot/_version.py
trainplot/plotting_function.py
trainplot/trainplot.py
trainplot/trainplot_keras.py
trainplot-0.4.0.dist-info/licenses/LICENSE
trainplot-0.4.0.dist-info/METADATA
trainplot-0.4.0.dist-info/WHEEL
trainplot-0.4.0.dist-info/top_level.txt
trainplot-0.4.0.dist-info/RECORD
