Metadata-Version: 2.4
Name: trainplot
Version: 0.4.0
Summary: Dynamically updating plots in Jupyter notebooks, e.g. for visualizing training progress.
Author-email: Jonas Loos <trainplot@jloos.de>
License: MIT License
Project-URL: Homepage, https://github.com/JonasLoos/trainplot
Requires-Python: >=3.9
License-File: LICENSE
Requires-Dist: ipython
Requires-Dist: anywidget>=0.9.0
Requires-Dist: numpy
Dynamic: license-file
